goodreads_api_client/__init__.py
goodreads_api_client/client.py
goodreads_api_client/exceptions.py
goodreads_api_client/transport.py
goodreads_api_client/resources/__init__.py
goodreads_api_client/resources/author.py
goodreads_api_client/resources/author_following.py
goodreads_api_client/resources/base.py
goodreads_api_client/resources/book.py
goodreads_api_client/resources/comment.py
goodreads_api_client/resources/event.py
goodreads_api_client/resources/follower.py
goodreads_api_client/resources/friend.py
goodreads_api_client/resources/group.py
goodreads_api_client/resources/list.py
goodreads_api_client/resources/notification.py
goodreads_api_client/resources/owned_book.py
goodreads_api_client/resources/quote.py
goodreads_api_client/resources/rating.py
goodreads_api_client/resources/read_status.py
goodreads_api_client/resources/recommendation.py
goodreads_api_client/resources/review.py
goodreads_api_client/resources/series.py
goodreads_api_client/resources/shelf.py
goodreads_api_client/resources/topic.py
goodreads_api_client/resources/update.py
goodreads_api_client/resources/user.py
goodreads_api_client/resources/user_shelf.py
goodreads_api_client/resources/user_status.py
goodreads_api_client/resources/work.py
goodreads_api_client/tests/__init__.py
goodreads_api_client/tests/conftest.py
goodreads_api_client/tests/test_client.py
goodreads_api_client/tests/test_transport.py
goodreads_api_client/tests/resources/__init__.py
goodreads_api_client/tests/resources/conftest.py
goodreads_api_client/tests/resources/test_author.py
goodreads_api_client/tests/resources/test_book.py
goodreads_api_client/tests/resources/test_comment.py
goodreads_api_client/tests/resources/test_event.py
goodreads_api_client/tests/resources/test_group.py
goodreads_api_client/tests/resources/test_read_status.py
goodreads_api_client/tests/resources/test_recommendation.py
goodreads_api_client/tests/resources/test_review.py
goodreads_api_client-0.1.0.dev4.dist-info/DESCRIPTION.rst
goodreads_api_client-0.1.0.dev4.dist-info/METADATA
goodreads_api_client-0.1.0.dev4.dist-info/RECORD
goodreads_api_client-0.1.0.dev4.dist-info/WHEEL
goodreads_api_client-0.1.0.dev4.dist-info/metadata.json
goodreads_api_client-0.1.0.dev4.dist-info/top_level.txt
