Metadata-Version: 2.1
Name: goodreads_api_client
Version: 0.1.0.dev4
Summary: A non-official client for Goodreads (https://goodreads.com)
Home-page: https://github.com/mdzhang/goodreads-api-client-python
Author: Michelle D. Zhang
Author-email: zhang.michelle.d@gmail.com
License: MIT
Platform: UNKNOWN
Classifier: Development Status :: 2 - Pre-Alpha
Classifier: Intended Audience :: Developers
Classifier: Natural Language :: English
Classifier: Operating System :: MacOS :: MacOS X
Classifier: Programming Language :: Python
Classifier: Programming Language :: Python :: 3.5
Classifier: Programming Language :: Python :: 3.6
Classifier: Topic :: Software Development
Provides-Extra: docs
Provides-Extra: test
Provides-Extra: publish
